{"t": "Chapter 32. Commission on Baseball.", "p": "/us/dc/council/code/titles/3/chapters/32", "et": "container", "dj": "/us/dc/council/code/index.json", "fh": "/us/dc/council/code/titles/3/chapters/32/index.full.html", "sc": "Chapter 32 of Title 3", "sp": "library|D.C. Code|3|32", "c": [{"t": "\u00a7 3\u20133201. Definitions [Expired]", "p": "/us/dc/council/code/sections/3-3201", "et": "section", "sc": "\u00a7 3-3201", "sp": "library|D.C. Code|3|32|3-3201"}, {"t": "\u00a7 3\u20133202. Established; duties [Expired]", "p": "/us/dc/council/code/sections/3-3202", "et": "section", "sc": "\u00a7 3-3202", "sp": "library|D.C. Code|3|32|3-3202"}, {"t": "\u00a7 3\u20133203. Composition; term of office; quorum; vacancies; reimbursement of members\u2019 expenses; meetings [Expired]", "p": "/us/dc/council/code/sections/3-3203", "et": "section", "sc": "\u00a7 3-3203", "sp": "library|D.C. Code|3|32|3-3203"}, {"t": "\u00a7 3\u20133204. Employment of consultant authorized; functions [Expired]", "p": "/us/dc/council/code/sections/3-3204", "et": "section", "sc": "\u00a7 3-3204", "sp": "library|D.C. Code|3|32|3-3204"}, {"t": "\u00a7 3\u20133205. Quarterly report [Expired]", "p": "/us/dc/council/code/sections/3-3205", "et": "section", "sc": "\u00a7 3-3205", "sp": "library|D.C. Code|3|32|3-3205"}, {"t": "\u00a7 3\u20133206. Final comprehensive report [Expired]", "p": "/us/dc/council/code/sections/3-3206", "et": "section", "sc": "\u00a7 3-3206", "sp": "library|D.C. Code|3|32|3-3206"}, {"t": "\u00a7 3\u20133207. Appropriations; grants; gifts and donations [Expired]", "p": "/us/dc/council/code/sections/3-3207", "et": "section", "sc": "\u00a7 3-3207", "sp": "library|D.C. Code|3|32|3-3207"}, {"t": "\u00a7 3\u20133208. District of Columbia Commission on Baseball Fund [Expired]", "p": "/us/dc/council/code/sections/3-3208", "et": "section", "sc": "\u00a7 3-3208", "sp": "library|D.C. Code|3|32|3-3208"}, {"t": "\u00a7 3\u20133209. Establishment [Expired]", "p": "/us/dc/council/code/sections/3-3209", "et": "section", "sc": "\u00a7 3-3209", "sp": "library|D.C. Code|3|32|3-3209"}, {"t": "\u00a7 3\u20133210. Composition; vacancies; quorum; meetings [Expired]", "p": "/us/dc/council/code/sections/3-3210", "et": "section", "sc": "\u00a7 3-3210", "sp": "library|D.C. Code|3|32|3-3210"}, {"t": "\u00a7 3\u20133211. Compensation [Expired]", "p": "/us/dc/council/code/sections/3-3211", "et": "section", "sc": "\u00a7 3-3211", "sp": "library|D.C. Code|3|32|3-3211"}, {"t": "\u00a7 3\u20133212. Cmployment of consultant [Expired]", "p": "/us/dc/council/code/sections/3-3212", "et": "section", "sc": "\u00a7 3-3212", "sp": "library|D.C. Code|3|32|3-3212"}, {"t": "\u00a7 3\u20133213. Comprehensive report [Expired]", "p": "/us/dc/council/code/sections/3-3213", "et": "section", "sc": "\u00a7 3-3213", "sp": "library|D.C. Code|3|32|3-3213"}, {"t": "\u00a7 3\u20133214. Appropriations; grants; gifts and donations [Expired]", "p": "/us/dc/council/code/sections/3-3214", "et": "section", "sc": "\u00a7 3-3214", "sp": "library|D.C. Code|3|32|3-3214"}, {"t": "\u00a7 3\u20133215. Baseball fund [Expired]", "p": "/us/dc/council/code/sections/3-3215", "et": "section", "sc": "\u00a7 3-3215", "sp": "library|D.C. Code|3|32|3-3215"}]}