{"t": "D.C. Law 22-28. Unity Health Care, Inc. Certificate of Need Maximum Fee Establishment Temporary Amendment Act of 2017.", "p": "/us/dc/council/laws/22-28", "et": "document", "sc": "D.C. Law 22-28", "sp": "library|dclaws|22|temporary|D.C. Law 22-28", "sd": true, "c": [{"t": "\u00a7 2.", "p": "/us/dc/council/laws/22-28#\u00a72", "et": "section", "sc": "\u00a7 2", "sp": "library|dclaws|22|temporary|D.C. Law 22-28|2", "x": "Section 21 of the Health Services Planning Program Re-Establishment Act of "}, {"t": "\u00a7 3. Fiscal impact statement.", "p": "/us/dc/council/laws/22-28#\u00a73", "et": "section", "sc": "\u00a7 3", "sp": "library|dclaws|22|temporary|D.C. Law 22-28|3"}, {"t": "\u00a7 4. Effective date.", "p": "/us/dc/council/laws/22-28#\u00a74", "et": "section", "sc": "\u00a7 4", "sp": "library|dclaws|22|temporary|D.C. Law 22-28|4", "c": [{"t": "(a)", "p": "/us/dc/council/laws/22-28#\u00a74(a)", "et": "para", "sc": "\u00a7 4(a)", "x": "This act shall take effect following approval by the Mayor (or in the event"}, {"t": "(b)", "p": "/us/dc/council/laws/22-28#\u00a74(b)", "et": "para", "sc": "\u00a7 4(b)", "x": "This act shall expire after 225 days of its having taken effect."}]}]}