{"t": "Chapter 35. Commission for Men.", "p": "/us/dc/council/code/titles/3/chapters/35", "et": "container", "dj": "/us/dc/council/code/index.json", "fh": "/us/dc/council/code/titles/3/chapters/35/index.full.html", "sc": "Chapter 35 of Title 3", "sp": "library|D.C. Code|3|35", "c": [{"t": "\u00a7 3\u20133501. Establishment of advisory task force on men. [Expired]", "p": "/us/dc/council/code/sections/3-3501", "et": "section", "sc": "\u00a7 3-3501", "sp": "library|D.C. Code|3|35|3-3501"}, {"t": "\u00a7 3\u20133502. Establishment of Commission for Men. [Expired]", "p": "/us/dc/council/code/sections/3-3502", "et": "section", "sc": "\u00a7 3-3502", "sp": "library|D.C. Code|3|35|3-3502"}, {"t": "\u00a7 3\u20133503. Qualifications; terms of office. [Expired]", "p": "/us/dc/council/code/sections/3-3503", "et": "section", "sc": "\u00a7 3-3503", "sp": "library|D.C. Code|3|35|3-3503"}, {"t": "\u00a7 3\u20133504. Compensation. [Expired]", "p": "/us/dc/council/code/sections/3-3504", "et": "section", "sc": "\u00a7 3-3504", "sp": "library|D.C. Code|3|35|3-3504"}, {"t": "\u00a7 3\u20133505. Powers of the Commission. [Expired]", "p": "/us/dc/council/code/sections/3-3505", "et": "section", "sc": "\u00a7 3-3505", "sp": "library|D.C. Code|3|35|3-3505"}, {"t": "\u00a7 3\u20133506. Administration. [Expired]", "p": "/us/dc/council/code/sections/3-3506", "et": "section", "sc": "\u00a7 3-3506", "sp": "library|D.C. Code|3|35|3-3506"}]}