{"t": "D.C. Act 23-199. Student Medical Marijuana Patient Fairness Congressional Review Emergency Amendment Act of 2019.", "p": "/us/dc/council/acts/23-199", "et": "document", "dj": "/us/dc/council/acts/23-199/index.json", "fh": "/us/dc/council/acts/23-199/index.full.html", "sc": "D.C. Act 23-199", "sp": "library|dclaws|23|emergency|D.C. Act 23-199", "sd": true, "c": [{"t": "\u00a7 2.", "p": "/us/dc/council/acts/23-199#\u00a72", "et": "section", "sc": "\u00a7 2", "sp": "library|dclaws|23|emergency|D.C. Act 23-199|2", "c": [{"t": "(a)", "p": "/us/dc/council/acts/23-199#\u00a72(a)", "et": "para", "sc": "\u00a7 2(a)", "x": "Paragraph (1) is amended by striking the phrase \"Medical marijuana shall\" a"}, {"t": "(b)", "p": "/us/dc/council/acts/23-199#\u00a72(b)", "et": "para", "sc": "\u00a7 2(b)", "x": "A new paragraph (4) is added to read as follows:"}], "x": "Section 4(b) of the Legalization of Marijuana for Medical Treatment Initiat"}, {"t": "\u00a7 3.", "p": "/us/dc/council/acts/23-199#\u00a73", "et": "section", "sc": "\u00a7 3", "sp": "library|dclaws|23|emergency|D.C. Act 23-199|3", "x": "Section 4 of the Student Access to Treatment Act of 2007, effective Februar"}, {"t": "\u00a7 4. Fiscal impact statement.", "p": "/us/dc/council/acts/23-199#\u00a74", "et": "section", "sc": "\u00a7 4", "sp": "library|dclaws|23|emergency|D.C. Act 23-199|4"}, {"t": "\u00a7 5. Effective date.", "p": "/us/dc/council/acts/23-199#\u00a75", "et": "section", "sc": "\u00a7 5", "sp": "library|dclaws|23|emergency|D.C. Act 23-199|5"}]}