{"t": "ch. 486.", "p": "/us/congress/laws/public/82-2-ch486", "et": "document", "sc": "Stat. 82-2-ch486", "sp": "library|fedlaws|82|Stat. 82-2-ch486", "sd": true, "c": [{"t": "\u00a7 1.", "p": "/us/congress/laws/public/82-2-ch486#\u00a71", "et": "section", "sc": "\u00a7 1", "sp": "library|fedlaws|82|Stat. 82-2-ch486|1"}, {"t": "\u00a7 2.", "p": "/us/congress/laws/public/82-2-ch486#\u00a72", "et": "section", "sc": "\u00a7 2", "sp": "library|fedlaws|82|Stat. 82-2-ch486|2"}, {"t": "\u00a7 3.", "p": "/us/congress/laws/public/82-2-ch486#\u00a73", "et": "section", "sc": "\u00a7 3", "sp": "library|fedlaws|82|Stat. 82-2-ch486|3"}]}