{"t": "D.C. Law 24-127. Reopen Washington DC Alcoholic Beverage Regulation Amendment Act of 2022.", "p": "/us/dc/council/laws/24-127", "et": "document", "sc": "D.C. Law 24-127", "sp": "library|dclaws|24|permanent|effective|D.C. Law 24-127", "sd": true, "c": [{"t": "\u00a7 2.", "p": "/us/dc/council/laws/24-127#\u00a72", "et": "section", "sc": "\u00a7 2", "sp": "library|dclaws|24|permanent|effective|D.C. Law 24-127|2", "c": [{"t": "(a)", "p": "/us/dc/council/laws/24-127#\u00a72(a)", "et": "para", "sc": "\u00a7 2(a)", "c": [{"t": "(1)", "p": "/us/dc/council/laws/24-127#\u00a72(a)(1)", "et": "para", "sc": "\u00a7 2(a)(1)", "x": "The table of contents for Subchapter II is amended by adding new section de"}, {"t": "(2)", "p": "/us/dc/council/laws/24-127#\u00a72(a)(2)", "et": "para", "sc": "\u00a7 2(a)(2)", "c": [{"t": "(A)", "p": "/us/dc/council/laws/24-127#\u00a72(a)(2)(A)", "et": "para", "sc": "\u00a7 2(a)(2)(A)", "x": "A new paragraph (4A) is added to read as follows:"}, {"t": "(B)", "p": "/us/dc/council/laws/24-127#\u00a72(a)(2)(B)", "et": "para", "sc": "\u00a7 2(a)(2)(B)", "x": "Paragraph (12) is amended by striking the phrase \"licensed wholesalers for "}, {"t": "(C)", "p": "/us/dc/council/laws/24-127#\u00a72(a)(2)(C)", "et": "para", "sc": "\u00a7 2(a)(2)(C)", "x": "New paragraphs (14A) and (14B) are added to read as follows:"}, {"t": "(D)", "p": "/us/dc/council/laws/24-127#\u00a72(a)(2)(D)", "et": "para", "sc": "\u00a7 2(a)(2)(D)", "x": "Paragraph (15A) is repealed."}, {"t": "(E)", "p": "/us/dc/council/laws/24-127#\u00a72(a)(2)(E)", "et": "para", "sc": "\u00a7 2(a)(2)(E)", "x": "A new paragraph (15B) is added to read as follows:"}, {"t": "(F)", "p": "/us/dc/council/laws/24-127#\u00a72(a)(2)(F)", "et": "para", "sc": "\u00a7 2(a)(2)(F)", "x": "A new paragraph (17A) is added to read as follows:"}, {"t": "(G)", "p": "/us/dc/council/laws/24-127#\u00a72(a)(2)(G)", "et": "para", "sc": "\u00a7 2(a)(2)(G)", "x": "A new paragraph (18A) is added to read as follows:"}, {"t": "(H)", "p": "/us/dc/council/laws/24-127#\u00a72(a)(2)(H)", "et": "para", "sc": "\u00a7 2(a)(2)(H)", "x": "Paragraph (21A) is amended by striking the phrase \"and disc jockeys\" and in"}, {"t": "(I)", "p": "/us/dc/council/laws/24-127#\u00a72(a)(2)(I)", "et": "para", "sc": "\u00a7 2(a)(2)(I)", "x": "A new paragraph (31A) is added to read as follows:"}, {"t": "(J)", "p": "/us/dc/council/laws/24-127#\u00a72(a)(2)(J)", "et": "para", "sc": "\u00a7 2(a)(2)(J)", "x": "A new paragraph (38B) is added to read as follows:"}, {"t": "(K)", "p": "/us/dc/council/laws/24-127#\u00a72(a)(2)(K)", "et": "para", "sc": "\u00a7 2(a)(2)(K)", "x": "Paragraphs (44) and (44A) are redesignated as paragraphs (44A) and (44B), r"}, {"t": "(L)", "p": "/us/dc/council/laws/24-127#\u00a72(a)(2)(L)", "et": "para", "sc": "\u00a7 2(a)(2)(L)", "x": "A new paragraph (44) is added to read as follows:"}, {"t": "(M)", "p": "/us/dc/council/laws/24-127#\u00a72(a)(2)(M)", "et": "para", "sc": "\u00a7 2(a)(2)(M)", "x": "Paragraph (49)(B) is amended by striking the figure \"15%\" and inserting the"}, {"t": "(N)", "p": "/us/dc/council/laws/24-127#\u00a72(a)(2)(N)", "et": "para", "sc": "\u00a7 2(a)(2)(N)", "x": "A new paragraph (52A) is added to read as follows:"}], "x": "Section 25-101 is amended as follows:"}, {"t": "(3)", "p": "/us/dc/council/laws/24-127#\u00a72(a)(3)", "et": "para", "sc": "\u00a7 2(a)(3)", "x": "Section 25-112 is amended by adding a new subsection (i) to read as follows"}, {"t": "(4)", "p": "/us/dc/council/laws/24-127#\u00a72(a)(4)", "et": "para", "sc": "\u00a7 2(a)(4)", "c": [{"t": "(A)", "p": "/us/dc/council/laws/24-127#\u00a72(a)(4)(A)", "et": "para", "sc": "\u00a7 2(a)(4)(A)", "c": [{"t": "(i)", "p": "/us/dc/council/laws/24-127#\u00a72(a)(4)(A)(i)", "et": "para", "sc": "\u00a7 2(a)(4)(A)(i)", "x": "Paragraph (3) is amended by adding a new subparagraph (D) to read as follow"}, {"t": "(ii)", "p": "/us/dc/council/laws/24-127#\u00a72(a)(4)(A)(ii)", "et": "para", "sc": "\u00a7 2(a)(4)(A)(ii)", "x": "A new paragraph (6) is added to read as follows:"}], "x": "Subsection (a) is amended as follows:"}, {"t": "(B)", "p": "/us/dc/council/laws/24-127#\u00a72(a)(4)(B)", "et": "para", "sc": "\u00a7 2(a)(4)(B)", "c": [{"t": "(i)", "p": "/us/dc/council/laws/24-127#\u00a72(a)(4)(B)(i)", "et": "para", "sc": "\u00a7 2(a)(4)(B)(i)", "x": "Paragraph (4) is repealed."}, {"t": "(ii)", "p": "/us/dc/council/laws/24-127#\u00a72(a)(4)(B)(ii)", "et": "para", "sc": "\u00a7 2(a)(4)(B)(ii)", "x": "Paragraph (5) is amended to read as follows:"}], "x": "Subsection (b) is amended as follows:"}, {"t": "(C)", "p": "/us/dc/council/laws/24-127#\u00a72(a)(4)(C)", "et": "para", "sc": "\u00a7 2(a)(4)(C)", "x": "Subsection (c)(4) is repealed."}, {"t": "(D)", "p": "/us/dc/council/laws/24-127#\u00a72(a)(4)(D)", "et": "para", "sc": "\u00a7 2(a)(4)(D)", "x": "Subsection (e)(7) is amended to read as follows:"}, {"t": "(E)", "p": "/us/dc/council/laws/24-127#\u00a72(a)(4)(E)", "et": "para", "sc": "\u00a7 2(a)(4)(E)", "c": [{"t": "(i)", "p": "/us/dc/council/laws/24-127#\u00a72(a)(4)(E)(i)", "et": "para", "sc": "\u00a7 2(a)(4)(E)(i)", "x": "Paragraph (5) is amended to read as follows:"}, {"t": "(ii)", "p": "/us/dc/council/laws/24-127#\u00a72(a)(4)(E)(ii)", "et": "para", "sc": "\u00a7 2(a)(4)(E)(ii)", "x": "A new subparagraph (6) is added to read as follows:"}], "x": "Subsection (i) is amended as follows:"}], "x": "Section 25-113 is amended as follows:"}, {"t": "(5)", "p": "/us/dc/council/laws/24-127#\u00a72(a)(5)", "et": "para", "sc": "\u00a7 2(a)(5)", "c": [{"t": "(A)", "p": "/us/dc/council/laws/24-127#\u00a72(a)(5)(A)", "et": "para", "sc": "\u00a7 2(a)(5)(A)", "x": "Subsection (b)(2) is amended by striking the phrase \"8:00 a.m. and 12:00 a."}, {"t": "(B)", "p": "/us/dc/council/laws/24-127#\u00a72(a)(5)(B)", "et": "para", "sc": "\u00a7 2(a)(5)(B)", "x": "Subsection (c) is amended by striking the phrase \"8:00 a.m. and 12:00 a.m.\""}, {"t": "(C)", "p": "/us/dc/council/laws/24-127#\u00a72(a)(5)(C)", "et": "para", "sc": "\u00a7 2(a)(5)(C)", "x": "A new subsection (c-1) is added to read as follows:"}], "x": "Section 25-113.01 is amended as follows:"}, {"t": "(6)", "p": "/us/dc/council/laws/24-127#\u00a72(a)(6)", "et": "para", "sc": "\u00a7 2(a)(6)", "c": [{"t": "(A)", "p": "/us/dc/council/laws/24-127#\u00a72(a)(6)(A)", "et": "para", "sc": "\u00a7 2(a)(6)(A)", "c": [{"t": "(i)", "p": "/us/dc/council/laws/24-127#\u00a72(a)(6)(A)(i)", "et": "para", "sc": "\u00a7 2(a)(6)(A)(i)", "x": "Paragraph (1) is amended by striking the phrase \"licensed wholesalers for t"}, {"t": "(ii)", "p": "/us/dc/council/laws/24-127#\u00a72(a)(6)(A)(ii)", "et": "para", "sc": "\u00a7 2(a)(6)(A)(ii)", "x": "A new paragraph (5) is added to read as follows:"}], "x": "Subsection (a) is amended as follows:"}, {"t": "(B)", "p": "/us/dc/council/laws/24-127#\u00a72(a)(6)(B)", "et": "para", "sc": "\u00a7 2(a)(6)(B)", "x": "Subsection (a-2) is amended by striking the phrase \"beer pub endorsement\" w"}], "x": "Section 25-117 is amended as follows:"}, {"t": "(7)", "p": "/us/dc/council/laws/24-127#\u00a72(a)(7)", "et": "para", "sc": "\u00a7 2(a)(7)", "c": [{"t": "(A)", "p": "/us/dc/council/laws/24-127#\u00a72(a)(7)(A)", "et": "para", "sc": "\u00a7 2(a)(7)(A)", "x": "Subsection (c) is amended by striking the phrase \"a licensee shall\" and ins"}, {"t": "(B)", "p": "/us/dc/council/laws/24-127#\u00a72(a)(7)(B)", "et": "para", "sc": "\u00a7 2(a)(7)(B)", "x": "Subsection (e) is amended by striking the phrase \"8:00 a.m. and 12:00 a.m.\""}, {"t": "(C)", "p": "/us/dc/council/laws/24-127#\u00a72(a)(7)(C)", "et": "para", "sc": "\u00a7 2(a)(7)(C)", "x": "Subsection (f)(1) is amended by striking the phrase \"8:00 a.m. and 12:00 a."}, {"t": "(D)", "p": "/us/dc/council/laws/24-127#\u00a72(a)(7)(D)", "et": "para", "sc": "\u00a7 2(a)(7)(D)", "x": "Subsection (g)(1) is amended to read as follows:"}], "x": "Section 25-118 is amended as follows:"}, {"t": "(8)", "p": "/us/dc/council/laws/24-127#\u00a72(a)(8)", "et": "para", "sc": "\u00a7 2(a)(8)", "x": "Section 25-120(h) is amended by striking the phrase \"proof of certification"}, {"t": "(9)", "p": "/us/dc/council/laws/24-127#\u00a72(a)(9)", "et": "para", "sc": "\u00a7 2(a)(9)", "x": "Section 25-125(d)(2) is amended by striking the phrase \"7:00 a.m. to 12:00 "}, {"t": "(10)", "p": "/us/dc/council/laws/24-127#\u00a72(a)(10)", "et": "para", "sc": "\u00a7 2(a)(10)", "x": "New sections 25-130 and 25-131 are added to read as follows:"}], "x": "Chapter 1 is amended as follows:"}, {"t": "(b)", "p": "/us/dc/council/laws/24-127#\u00a72(b)", "et": "para", "sc": "\u00a7 2(b)", "c": [{"t": "(1)", "p": "/us/dc/council/laws/24-127#\u00a72(b)(1)", "et": "para", "sc": "\u00a7 2(b)(1)", "c": [{"t": "(A)", "p": "/us/dc/council/laws/24-127#\u00a72(b)(1)(A)", "et": "para", "sc": "\u00a7 2(b)(1)(A)", "x": "Subsection (a)(2) is amended to read as follows:"}, {"t": "(B)", "p": "/us/dc/council/laws/24-127#\u00a72(b)(1)(B)", "et": "para", "sc": "\u00a7 2(b)(1)(B)", "x": "Subsection (b) is amended to read as follows:"}, {"t": "(C)", "p": "/us/dc/council/laws/24-127#\u00a72(b)(1)(C)", "et": "para", "sc": "\u00a7 2(b)(1)(C)", "x": "Subsection (d) is repealed."}], "x": "Section 25-205 is amended as follows:"}], "x": "Chapter 2 is amended as follows:"}, {"t": "(c)", "p": "/us/dc/council/laws/24-127#\u00a72(c)", "et": "para", "sc": "\u00a7 2(c)", "c": [{"t": "(1)", "p": "/us/dc/council/laws/24-127#\u00a72(c)(1)", "et": "para", "sc": "\u00a7 2(c)(1)", "c": [{"t": "(A)", "p": "/us/dc/council/laws/24-127#\u00a72(c)(1)(A)", "et": "para", "sc": "\u00a7 2(c)(1)(A)", "c": [{"t": "(i)", "p": "/us/dc/council/laws/24-127#\u00a72(c)(1)(A)(i)", "et": "para", "sc": "\u00a7 2(c)(1)(A)(i)", "x": "A new paragraph (2A) is added to read as follows:"}, {"t": "(ii)", "p": "/us/dc/council/laws/24-127#\u00a72(c)(1)(A)(ii)", "et": "para", "sc": "\u00a7 2(c)(1)(A)(ii)", "x": "Paragraph (3) is amended by striking the phrase \"hold an interest in any ot"}, {"t": "(iii)", "p": "/us/dc/council/laws/24-127#\u00a72(c)(1)(A)(iii)", "et": "para", "sc": "\u00a7 2(c)(1)(A)(iii)", "x": "Paragraph (4) is amended to read as follows:"}, {"t": "(iv)", "p": "/us/dc/council/laws/24-127#\u00a72(c)(1)(A)(iv)", "et": "para", "sc": "\u00a7 2(c)(1)(A)(iv)", "x": "A new paragraph (5) is added to read as follows:"}], "x": "Subsection (a) is amended as follows:"}, {"t": "(B)", "p": "/us/dc/council/laws/24-127#\u00a72(c)(1)(B)", "et": "para", "sc": "\u00a7 2(c)(1)(B)", "x": "Subsection (c-1) is amended by striking the phrase \"class CR or DR\" and ins"}, {"t": "(C)", "p": "/us/dc/council/laws/24-127#\u00a72(c)(1)(C)", "et": "para", "sc": "\u00a7 2(c)(1)(C)", "x": "A new subsection (c-2) is added to read as follows:"}], "x": "Section 25-303 is amended as follows:"}, {"t": "(2)", "p": "/us/dc/council/laws/24-127#\u00a72(c)(2)", "et": "para", "sc": "\u00a7 2(c)(2)", "x": "Section 25-314(b) is amended by adding a new paragraph (12) to read as foll"}, {"t": "(3)", "p": "/us/dc/council/laws/24-127#\u00a72(c)(3)", "et": "para", "sc": "\u00a7 2(c)(3)", "x": "Section 25-331(e) is amended by striking the phrase \"class AI,\" and inserti"}, {"t": "(4)", "p": "/us/dc/council/laws/24-127#\u00a72(c)(4)", "et": "para", "sc": "\u00a7 2(c)(4)", "c": [{"t": "(A)", "p": "/us/dc/council/laws/24-127#\u00a72(c)(4)(A)", "et": "para", "sc": "\u00a7 2(c)(4)(A)", "x": "A new subsection (c-2) is added to read as follows:"}, {"t": "(B)", "p": "/us/dc/council/laws/24-127#\u00a72(c)(4)(B)", "et": "para", "sc": "\u00a7 2(c)(4)(B)", "x": "A new subsection (f) is added to read as follows:"}], "x": "Section 25-333 is amended as follows:"}, {"t": "(5)", "p": "/us/dc/council/laws/24-127#\u00a72(c)(5)", "et": "para", "sc": "\u00a7 2(c)(5)", "x": "Section 25-339 is amended to read as follows:"}, {"t": "(6)", "p": "/us/dc/council/laws/24-127#\u00a72(c)(6)", "et": "para", "sc": "\u00a7 2(c)(6)", "x": "Section 25-342 is amended by adding a new subsection (d) to read as follows"}, {"t": "(7)", "p": "/us/dc/council/laws/24-127#\u00a72(c)(7)", "et": "para", "sc": "\u00a7 2(c)(7)", "c": [{"t": "(A)", "p": "/us/dc/council/laws/24-127#\u00a72(c)(7)(A)", "et": "para", "sc": "\u00a7 2(c)(7)(A)", "x": "A new subsection (b-1) is added to read as follows:"}, {"t": "(B)", "p": "/us/dc/council/laws/24-127#\u00a72(c)(7)(B)", "et": "para", "sc": "\u00a7 2(c)(7)(B)", "x": "New subsections (d) and (e) are added to read as follows :"}], "x": "Section 25-343 is amended as follows:"}, {"t": "(8)", "p": "/us/dc/council/laws/24-127#\u00a72(c)(8)", "et": "para", "sc": "\u00a7 2(c)(8)", "c": [{"t": "(A)", "p": "/us/dc/council/laws/24-127#\u00a72(c)(8)(A)", "et": "para", "sc": "\u00a7 2(c)(8)(A)", "x": "Subsections (e), (f), and (g) are repealed."}, {"t": "(B)", "p": "/us/dc/council/laws/24-127#\u00a72(c)(8)(B)", "et": "para", "sc": "\u00a7 2(c)(8)(B)", "x": "A new subsection (h) is added to read as follows:"}], "x": "Section 25-374 is amended as follows:"}], "x": "Chapter 3 is amended as follows:"}, {"t": "(d)", "p": "/us/dc/council/laws/24-127#\u00a72(d)", "et": "para", "sc": "\u00a7 2(d)", "c": [{"t": "(1)", "p": "/us/dc/council/laws/24-127#\u00a72(d)(1)", "et": "para", "sc": "\u00a7 2(d)(1)", "x": "Section 25-401(c) is amended by striking the phrase \"shall sign a notarized"}, {"t": "(2)", "p": "/us/dc/council/laws/24-127#\u00a72(d)(2)", "et": "para", "sc": "\u00a7 2(d)(2)", "c": [{"t": "(A)", "p": "/us/dc/council/laws/24-127#\u00a72(d)(2)(A)", "et": "para", "sc": "\u00a7 2(d)(2)(A)", "x": "Subsection (d) is repealed."}, {"t": "(B)", "p": "/us/dc/council/laws/24-127#\u00a72(d)(2)(B)", "et": "para", "sc": "\u00a7 2(d)(2)(B)", "x": "A new subsection (e) is added to read as follows:"}], "x": "Section 25-402 is amended as follows:"}, {"t": "(3)", "p": "/us/dc/council/laws/24-127#\u00a72(d)(3)", "et": "para", "sc": "\u00a7 2(d)(3)", "c": [{"t": "(A)", "p": "/us/dc/council/laws/24-127#\u00a72(d)(3)(A)", "et": "para", "sc": "\u00a7 2(d)(3)(A)", "x": "Subsection (a) is amended by striking the phrase \"verify, by affidavit\" and"}, {"t": "(B)", "p": "/us/dc/council/laws/24-127#\u00a72(d)(3)(B)", "et": "para", "sc": "\u00a7 2(d)(3)(B)", "x": "Subsection (e) is repealed."}], "x": "Section 25-403 is amended as follows:"}, {"t": "(4)", "p": "/us/dc/council/laws/24-127#\u00a72(d)(4)", "et": "para", "sc": "\u00a7 2(d)(4)", "c": [{"t": "(A)", "p": "/us/dc/council/laws/24-127#\u00a72(d)(4)(A)", "et": "para", "sc": "\u00a7 2(d)(4)(A)", "x": "Subsection (a) is amended by striking the phrase \"the Board under 25-404, o"}, {"t": "(B)", "p": "/us/dc/council/laws/24-127#\u00a72(d)(4)(B)", "et": "para", "sc": "\u00a7 2(d)(4)(B)", "x": "Subsection (e) is amended to read as follows:"}, {"t": "(C)", "p": "/us/dc/council/laws/24-127#\u00a72(d)(4)(C)", "et": "para", "sc": "\u00a7 2(d)(4)(C)", "x": "Subsection (h) is amended by striking the phrase \"after 12:00 a.m.\" and ins"}], "x": "Section 25-421 is amended as follows:"}, {"t": "(5)", "p": "/us/dc/council/laws/24-127#\u00a72(d)(5)", "et": "para", "sc": "\u00a7 2(d)(5)", "x": "Section 25-443 is amended to read as follows:"}], "x": "Chapter 4 is amended as follows:"}, {"t": "(e)", "p": "/us/dc/council/laws/24-127#\u00a72(e)", "et": "para", "sc": "\u00a7 2(e)", "c": [{"t": "(1)", "p": "/us/dc/council/laws/24-127#\u00a72(e)(1)", "et": "para", "sc": "\u00a7 2(e)(1)", "x": "The table of contents is amended by adding a new section designation to rea"}, {"t": "(2)", "p": "/us/dc/council/laws/24-127#\u00a72(e)(2)", "et": "para", "sc": "\u00a7 2(e)(2)", "x": "Section 25-504 is amended by adding a new subsection (c) to read as follows"}, {"t": "(3)", "p": "/us/dc/council/laws/24-127#\u00a72(e)(3)", "et": "para", "sc": "\u00a7 2(e)(3)", "x": "Section 25-508 is amended by striking the period and inserting the phrase \""}, {"t": "(4)", "p": "/us/dc/council/laws/24-127#\u00a72(e)(4)", "et": "para", "sc": "\u00a7 2(e)(4)", "x": "A new section 25-513 is added to read as follows:"}], "x": "Chapter 5 is amended as follows:"}, {"t": "(f)", "p": "/us/dc/council/laws/24-127#\u00a72(f)", "et": "para", "sc": "\u00a7 2(f)", "c": [{"t": "(1)", "p": "/us/dc/council/laws/24-127#\u00a72(f)(1)", "et": "para", "sc": "\u00a7 2(f)(1)", "c": [{"t": "(A)", "p": "/us/dc/council/laws/24-127#\u00a72(f)(1)(A)", "et": "para", "sc": "\u00a7 2(f)(1)(A)", "x": "A new section designation 25-704 is added to read as follows:"}, {"t": "(B)", "p": "/us/dc/council/laws/24-127#\u00a72(f)(1)(B)", "et": "para", "sc": "\u00a7 2(f)(1)(B)", "x": "The section designation for section 25-766 is amended to read as follows:"}, {"t": "(C)", "p": "/us/dc/council/laws/24-127#\u00a72(f)(1)(C)", "et": "para", "sc": "\u00a7 2(f)(1)(C)", "x": "A new section designation 25-767 is added to read as follows:"}], "x": "The table of contents is amended as follows:"}, {"t": "(2)", "p": "/us/dc/council/laws/24-127#\u00a72(f)(2)", "et": "para", "sc": "\u00a7 2(f)(2)", "x": "A new section 25-704 is added to read as follows:"}, {"t": "(3)", "p": "/us/dc/council/laws/24-127#\u00a72(f)(3)", "et": "para", "sc": "\u00a7 2(f)(3)", "x": "Section 25-711(f) is amended to read as follows:"}, {"t": "(4)", "p": "/us/dc/council/laws/24-127#\u00a72(f)(4)", "et": "para", "sc": "\u00a7 2(f)(4)", "c": [{"t": "(A)", "p": "/us/dc/council/laws/24-127#\u00a72(f)(4)(A)", "et": "para", "sc": "\u00a7 2(f)(4)(A)", "x": "Subsections (a), (a-1), and (b) are amended to read as follows:"}, {"t": "(B)", "p": "/us/dc/council/laws/24-127#\u00a72(f)(4)(B)", "et": "para", "sc": "\u00a7 2(f)(4)(B)", "x": "Subsection (d) is amended by striking the phrase \"and the homes of District"}], "x": "Section 25-721 is amended as follows:"}, {"t": "(5)", "p": "/us/dc/council/laws/24-127#\u00a72(f)(5)", "et": "para", "sc": "\u00a7 2(f)(5)", "c": [{"t": "(A)", "p": "/us/dc/council/laws/24-127#\u00a72(f)(5)(A)", "et": "para", "sc": "\u00a7 2(f)(5)(A)", "x": "Subsection (a) is amended by striking the phrase \"alcoholic beverages\" and "}, {"t": "(B)", "p": "/us/dc/council/laws/24-127#\u00a72(f)(5)(B)", "et": "para", "sc": "\u00a7 2(f)(5)(B)", "x": "Subsection (b) is amended to read as follows:"}], "x": "Section 25-722 is amended as follows:"}, {"t": "(6)", "p": "/us/dc/council/laws/24-127#\u00a72(f)(6)", "et": "para", "sc": "\u00a7 2(f)(6)", "c": [{"t": "(A)", "p": "/us/dc/council/laws/24-127#\u00a72(f)(6)(A)", "et": "para", "sc": "\u00a7 2(f)(6)(A)", "c": [{"t": "(i)", "p": "/us/dc/council/laws/24-127#\u00a72(f)(6)(A)(i)", "et": "para", "sc": "\u00a7 2(f)(6)(A)(i)", "x": "Strike the phrase \"and subsections (c), (d), and (g)\" and insert the phrase"}, {"t": "(ii)", "p": "/us/dc/council/laws/24-127#\u00a72(f)(6)(A)(ii)", "et": "para", "sc": "\u00a7 2(f)(6)(A)(ii)", "x": "Strike the phrase \"on-premises retailer's\" and insert the phrase \"on-premis"}, {"t": "(iii)", "p": "/us/dc/council/laws/24-127#\u00a72(f)(6)(A)(iii)", "et": "para", "sc": "\u00a7 2(f)(6)(A)(iii)", "x": "Strike the word \"consume\" and insert the phrase \"permit the consumption of\""}], "x": "Subsection (b) is amended as follows:"}, {"t": "(B)", "p": "/us/dc/council/laws/24-127#\u00a72(f)(6)(B)", "et": "para", "sc": "\u00a7 2(f)(6)(B)", "x": "New subsections (b-1) and (b-2) are added to read as follows:"}, {"t": "(C)", "p": "/us/dc/council/laws/24-127#\u00a72(f)(6)(C)", "et": "para", "sc": "\u00a7 2(f)(6)(C)", "c": [{"t": "(i)", "p": "/us/dc/council/laws/24-127#\u00a72(f)(6)(C)(i)", "et": "para", "sc": "\u00a7 2(f)(6)(C)(i)", "x": "Paragraph (1) is amended by striking the word \"consume\" and inserting the p"}, {"t": "(ii)", "p": "/us/dc/council/laws/24-127#\u00a72(f)(6)(C)(ii)", "et": "para", "sc": "\u00a7 2(f)(6)(C)(ii)", "x": "Paragraph (2) is amended by striking the word \"consume\" and inserting the p"}, {"t": "(iii)", "p": "/us/dc/council/laws/24-127#\u00a72(f)(6)(C)(iii)", "et": "para", "sc": "\u00a7 2(f)(6)(C)(iii)", "x": "Paragraph (4) is amended by striking the phrase \"and a public safety plan\"."}], "x": "Subsection (c) is amended as follows:"}, {"t": "(D)", "p": "/us/dc/council/laws/24-127#\u00a72(f)(6)(D)", "et": "para", "sc": "\u00a7 2(f)(6)(D)", "c": [{"t": "(i)", "p": "/us/dc/council/laws/24-127#\u00a72(f)(6)(D)(i)", "et": "para", "sc": "\u00a7 2(f)(6)(D)(i)", "x": "Strike the phrase \"manufacturer's license\" and insert the phrase \"manufactu"}, {"t": "(ii)", "p": "/us/dc/council/laws/24-127#\u00a72(f)(6)(D)(ii)", "et": "para", "sc": "\u00a7 2(f)(6)(D)(ii)", "x": "Strike the word \"consume\" and insert the phrase \"permit the consumption of\""}, {"t": "(iii)", "p": "/us/dc/council/laws/24-127#\u00a72(f)(6)(D)(iii)", "et": "para", "sc": "\u00a7 2(f)(6)(D)(iii)", "x": "Subparagraph (A) is amended by striking the phrase \"and a public safety pla"}], "x": "Subsection (e)(1) is amended as follows:"}], "x": "Section 25-723 is amended as follows:"}, {"t": "(7)", "p": "/us/dc/council/laws/24-127#\u00a72(f)(7)", "et": "para", "sc": "\u00a7 2(f)(7)", "x": "Section 25-725(b)(3) is amended by striking the phrase \"commercial or manuf"}, {"t": "(8)", "p": "/us/dc/council/laws/24-127#\u00a72(f)(8)", "et": "para", "sc": "\u00a7 2(f)(8)", "x": "Section 25-733(b) is repealed."}, {"t": "(9)", "p": "/us/dc/council/laws/24-127#\u00a72(f)(9)", "et": "para", "sc": "\u00a7 2(f)(9)", "x": "Section 25-751(c) is repealed."}, {"t": "(10)", "p": "/us/dc/council/laws/24-127#\u00a72(f)(10)", "et": "para", "sc": "\u00a7 2(f)(10)", "x": "Section 25-766 is amended to read as follows:"}, {"t": "(11)", "p": "/us/dc/council/laws/24-127#\u00a72(f)(11)", "et": "para", "sc": "\u00a7 2(f)(11)", "x": "A new section 25-767 is added to read as follows:"}, {"t": "(12)", "p": "/us/dc/council/laws/24-127#\u00a72(f)(12)", "et": "para", "sc": "\u00a7 2(f)(12)", "c": [{"t": "(A)", "p": "/us/dc/council/laws/24-127#\u00a72(f)(12)(A)", "et": "para", "sc": "\u00a7 2(f)(12)(A)", "c": [{"t": "(i)", "p": "/us/dc/council/laws/24-127#\u00a72(f)(12)(A)(i)", "et": "para", "sc": "\u00a7 2(f)(12)(A)(i)", "x": "Paragraph (1) is amended by striking the semicolon and inserting the phrase"}, {"t": "(ii)", "p": "/us/dc/council/laws/24-127#\u00a72(f)(12)(A)(ii)", "et": "para", "sc": "\u00a7 2(f)(12)(A)(ii)", "x": "Paragraph (2) is amended by striking the phrase \"; or\" and inserting a peri"}, {"t": "(iii)", "p": "/us/dc/council/laws/24-127#\u00a72(f)(12)(A)(iii)", "et": "para", "sc": "\u00a7 2(f)(12)(A)(iii)", "x": "Paragraph (3) is repealed."}], "x": "Subsection (a) is amended as follows:"}, {"t": "(B)", "p": "/us/dc/council/laws/24-127#\u00a72(f)(12)(B)", "et": "para", "sc": "\u00a7 2(f)(12)(B)", "c": [{"t": "(i)", "p": "/us/dc/council/laws/24-127#\u00a72(f)(12)(B)(i)", "et": "para", "sc": "\u00a7 2(f)(12)(B)(i)", "x": "Paragraph (1) is amended by striking the semicolon and inserting the phrase"}, {"t": "(ii)", "p": "/us/dc/council/laws/24-127#\u00a72(f)(12)(B)(ii)", "et": "para", "sc": "\u00a7 2(f)(12)(B)(ii)", "x": "Paragraph (2) is amended by striking the phrase \"; or\" and inserting a peri"}, {"t": "(iii)", "p": "/us/dc/council/laws/24-127#\u00a72(f)(12)(B)(iii)", "et": "para", "sc": "\u00a7 2(f)(12)(B)(iii)", "x": "Paragraph (3) is repealed."}], "x": "Subsection (b) is amended as follows:"}, {"t": "(C)", "p": "/us/dc/council/laws/24-127#\u00a72(f)(12)(C)", "et": "para", "sc": "\u00a7 2(f)(12)(C)", "x": "Subsection (f)(3) is amended by striking the phrase \"suspend the licensee\" "}, {"t": "(D)", "p": "/us/dc/council/laws/24-127#\u00a72(f)(12)(D)", "et": "para", "sc": "\u00a7 2(f)(12)(D)", "x": "A new subsection (f-1) is added to read as follows:"}, {"t": "(E)", "p": "/us/dc/council/laws/24-127#\u00a72(f)(12)(E)", "et": "para", "sc": "\u00a7 2(f)(12)(E)", "x": "A new subsection (h) is added to read as follows:"}], "x": "Section 25-781 is amended as follows:"}, {"t": "(13)", "p": "/us/dc/council/laws/24-127#\u00a72(f)(13)", "et": "para", "sc": "\u00a7 2(f)(13)", "x": "Section 25-783(e) is amended to read as follows:"}, {"t": "(14)", "p": "/us/dc/council/laws/24-127#\u00a72(f)(14)", "et": "para", "sc": "\u00a7 2(f)(14)", "x": "Section 25-791(c-1)(3) is amended by striking the phrase \"serving a suspens"}], "x": "Chapter 7 is amended as follows:"}, {"t": "(g)", "p": "/us/dc/council/laws/24-127#\u00a72(g)", "et": "para", "sc": "\u00a7 2(g)", "c": [{"t": "(1)", "p": "/us/dc/council/laws/24-127#\u00a72(g)(1)", "et": "para", "sc": "\u00a7 2(g)(1)", "x": "The table of contents is amended by adding a new Subchapter III designation"}, {"t": "(2)", "p": "/us/dc/council/laws/24-127#\u00a72(g)(2)", "et": "para", "sc": "\u00a7 2(g)(2)", "c": [{"t": "(A)", "p": "/us/dc/council/laws/24-127#\u00a72(g)(2)(A)", "et": "para", "sc": "\u00a7 2(g)(2)(A)", "x": "Paragraph (2) is amended by striking the phrase \"; or\" and inserting a semi"}, {"t": "(B)", "p": "/us/dc/council/laws/24-127#\u00a72(g)(2)(B)", "et": "para", "sc": "\u00a7 2(g)(2)(B)", "x": "Paragraph (3) is amended by striking the period and inserting the phrase \";"}, {"t": "(C)", "p": "/us/dc/council/laws/24-127#\u00a72(g)(2)(C)", "et": "para", "sc": "\u00a7 2(g)(2)(C)", "x": "A new paragraph (4) is added to read as follows:"}], "x": "Section 25-822 is amended as follows:"}, {"t": "(3)", "p": "/us/dc/council/laws/24-127#\u00a72(g)(3)", "et": "para", "sc": "\u00a7 2(g)(3)", "x": "Section 25-823(a)(5) is amended to read as follows:"}, {"t": "(4)", "p": "/us/dc/council/laws/24-127#\u00a72(g)(4)", "et": "para", "sc": "\u00a7 2(g)(4)", "x": "Section 25-826(a) is amended by striking the phrase \"safety of the public\" "}, {"t": "(5)", "p": "/us/dc/council/laws/24-127#\u00a72(g)(5)", "et": "para", "sc": "\u00a7 2(g)(5)", "c": [{"t": "(A)", "p": "/us/dc/council/laws/24-127#\u00a72(g)(5)(A)", "et": "para", "sc": "\u00a7 2(g)(5)(A)", "x": "Strike the phrase \"60-day period of review\" both times it appears and inser"}, {"t": "(B)", "p": "/us/dc/council/laws/24-127#\u00a72(g)(5)(B)", "et": "para", "sc": "\u00a7 2(g)(5)(B)", "x": "Strike the phrase \"deem disapproved\" and insert the phrase \"deemed approved"}], "x": "Section 25-830(a) is amended as follows:"}, {"t": "(6)", "p": "/us/dc/council/laws/24-127#\u00a72(g)(6)", "et": "para", "sc": "\u00a7 2(g)(6)", "x": "A new section 25-836 is added to read as follows:"}], "x": "Chapter 8 is amended as follows:"}], "x": "Title 25 of the District of Columbia Official Code is amended as follows:"}, {"t": "\u00a7 3. Fiscal impact statement.", "p": "/us/dc/council/laws/24-127#\u00a73", "et": "section", "sc": "\u00a7 3", "sp": "library|dclaws|24|permanent|effective|D.C. Law 24-127|3"}, {"t": "\u00a7 4. Effective date.", "p": "/us/dc/council/laws/24-127#\u00a74", "et": "section", "sc": "\u00a7 4", "sp": "library|dclaws|24|permanent|effective|D.C. Law 24-127|4"}]}